torax_muscle3/__init__.py
torax_muscle3/_version.py
torax_muscle3/torax_actor.py
torax_muscle3/utils.py
torax_muscle3/tests/__init__.py
torax_muscle3/tests/basic_config.py
torax_muscle3/tests/test_actor.py
torax_muscle3/tests/data/ITERhybrid_COCOS17_IDS_ddv4.nc
torax_muscle3-0.1.0.dist-info/licenses/LICENSE.txt
torax_muscle3-0.1.0.dist-info/METADATA
torax_muscle3-0.1.0.dist-info/WHEEL
torax_muscle3-0.1.0.dist-info/top_level.txt
torax_muscle3-0.1.0.dist-info/RECORD
