Metadata-Version: 2.4
Name: torax-muscle3
Version: 0.1.0
Summary: TORAX IMAS MUSCLE3 wrapper
Author-email: Mike Sanders <msanders@ignitioncomputing.com>
License: 
Project-URL: homepage, https://github.com/iterorganization/TORAX-MUSCLE3
Classifier: Development Status :: 3 - Alpha
Classifier: Environment :: Console
Classifier: Environment :: Plugins
Classifier: Framework :: Pytest
Classifier: Framework :: Sphinx
Classifier: Intended Audience :: Developers
Classifier: Intended Audience :: Science/Research
Classifier: Intended Audience :: System Administrators
Classifier: License :: OSI Approved :: Apache Software License
Classifier: Natural Language :: English
Classifier: Operating System :: POSIX
Classifier: Operating System :: POSIX :: Linux
Classifier: Programming Language :: Python
Classifier: Programming Language :: Python :: 3
Classifier: Programming Language :: Python :: 3.8
Classifier: Programming Language :: Python :: 3.9
Classifier: Programming Language :: Unix Shell
Classifier: Topic :: Scientific/Engineering
Classifier: Topic :: Scientific/Engineering :: Physics
Classifier: Topic :: Software Development :: Libraries
Classifier: Topic :: Software Development :: Libraries :: Python Modules
Classifier: Topic :: System
Classifier: Topic :: System :: Software Distribution
Classifier: Topic :: Utilities
Requires-Python: >=3.11
License-File: LICENSE.txt
Requires-Dist: numpy>=2
Requires-Dist: importlib_resources
Requires-Dist: rich
Requires-Dist: packaging
Requires-Dist: torax[dev]>=1.2.0
Requires-Dist: imas-python
Requires-Dist: muscle3
Provides-Extra: all
Requires-Dist: torax-muscle3[docs,linting,test]; extra == "all"
Provides-Extra: docs
Requires-Dist: sphinx<7.0.0,>=6.0.0; extra == "docs"
Requires-Dist: sphinx-autosummary-accessors>=0.1.2; extra == "docs"
Requires-Dist: sphinx_immaterial<0.12,>=0.11.0; extra == "docs"
Requires-Dist: recommonmark>=0.6; extra == "docs"
Provides-Extra: test
Requires-Dist: pytest>=5.4.1; extra == "test"
Requires-Dist: pytest-cov>=0.6; extra == "test"
Requires-Dist: pytest-xdist; extra == "test"
Requires-Dist: pytest-randomly; extra == "test"
Provides-Extra: linting
Requires-Dist: ruff; extra == "linting"
Requires-Dist: mypy; extra == "linting"
Dynamic: license-file
